{
  "id": 264,
  "podcastId": 1,
  "podcastTitle": "Harmontown",
  "title": "247 - Everything is Sexy When You Trust Someone",
  "description": "Jeff Davis returns with a fantastic reprise of the classic \u201CPringles Dick\u201D. Brandon Johnson passes the comptroller torch back to Jeff. Dan, Jeff, Spencer and Steve Levy create characters for their new D\u0026D campaign! Featuring Dan Harmon, Jeff Davis, Spe...",
  "runtime": 7230,
  "releaseDate": 1496843400.000000000,
  "showDate": null,
  "firstName": null,
  "middleName": null,
  "lastName": null,
  "personId": 0,
  "guid": "gid://art19-episode-locator/V0/X-FKCTfXtxPt7ZsraXa5sRvqsQZvzw5Yel_g56_FCHI",
  "audio": "https://chtbl.com/track/E2288/traffic.megaphone.fm/STA3321103982.mp3",
  "lastEpisodeId": 263,
  "nextEpisodeId": 265,
  "lastTitle": "246 - Your Description of a Birthday Would Make Vonnegut Kill Himself",
  "nextTitle": "248 - Come Out and Fight Like a Ghost"
}