{
  "id": 58,
  "podcastId": 1,
  "podcastTitle": "Harmontown",
  "title": "45 - Dan Took a Shower (Kumail Nanjiani, Bobcat Goldthwait)",
  "description": "A discussion of hygiene heats up with Kumail Nanjiani, then boils over when Bobcat Goldthwait drops by. In D\u0026D, zombies attack while Quark engages in advanced animal husbandry. This fabulous episode is unedited so we will just warn you of a small gli...",
  "runtime": 6688,
  "releaseDate": 1361406060.000000000,
  "showDate": null,
  "firstName": null,
  "middleName": null,
  "lastName": null,
  "personId": 0,
  "guid": "http://www.castmate.fm/play.mp3?u=harmontownpodcast\u0026i=2115",
  "audio": "https://chtbl.com/track/E2288/traffic.megaphone.fm/STA4031683895.mp3?updated=1554491420",
  "lastEpisodeId": 57,
  "nextEpisodeId": 59,
  "lastTitle": "44 - Dudes and Goo (DC Pierson, Kumail Nanjiani)",
  "nextTitle": "46 - Neigh Means Yay"
}