{
  "id": 181,
  "podcastId": 1,
  "podcastTitle": "Harmontown",
  "title": "166 - #CHIOPS",
  "description": "Comptroller Rob Schrab comes out of the gate yelling, an over zealous fan brings hot sauce to the stage and guest Amy Berg and Wil Wheaton play a game of Werewolf!",
  "runtime": 7813,
  "releaseDate": 1444185180.000000000,
  "showDate": null,
  "firstName": null,
  "middleName": null,
  "lastName": null,
  "personId": 0,
  "guid": "http://www.castmate.fm/play.mp3?u=harmontownpodcast\u0026i=9358",
  "audio": "https://chtbl.com/track/E2288/traffic.megaphone.fm/STA1155491856.mp3?updated=1561157788",
  "lastEpisodeId": 180,
  "nextEpisodeId": 182,
  "lastTitle": "165 - Where The Moon?",
  "nextTitle": "Lost Episode #15"
}